afk_slack_agent/__init__.py
afk_slack_agent/agent.py
afk_slack_agent/client.py
afk_slack_agent/config.py
afk_slack_agent/os_interaction_utils.py
afk_slack_agent-0.3.0.dist-info/AUTHORS.rst
afk_slack_agent-0.3.0.dist-info/LICENSE
afk_slack_agent-0.3.0.dist-info/METADATA
afk_slack_agent-0.3.0.dist-info/WHEEL
afk_slack_agent-0.3.0.dist-info/entry_points.txt
afk_slack_agent-0.3.0.dist-info/top_level.txt
afk_slack_agent-0.3.0.dist-info/RECORD
