Metadata-Version: 2.1
Name: afk-slack-agent
Version: 0.3.0
Summary: Signal your A.F.K. status on Slack automatically
Home-page: https://github.com/keul/afk_slack_agent
Author: Luca Fabbri
Author-email: lucafbb@gmail.com
License: Apache Software License 2.0
Keywords: afk_slack_agent
Classifier: Development Status :: 3 - Alpha
Classifier: Environment :: MacOS X
Classifier: Intended Audience :: End Users/Desktop
Classifier: License :: OSI Approved :: Apache Software License
Classifier: Natural Language :: English
Classifier: Programming Language :: Python :: 3
Classifier: Programming Language :: Python :: 3.10
Requires-Python: >=3.10
License-File: LICENSE
License-File: AUTHORS.rst
Requires-Dist: Click >=7.0
Requires-Dist: pyobjc-framework-notificationcenter
Requires-Dist: slack-sdk
Requires-Dist: psutil
